p_requests/__init__.py
p_requests/core.py
p_requests-0.0.2.dist-info/licenses/LICENSE
parallel_requests/__init__.py
parallel_requests/core.py
p_requests-0.0.2.dist-info/METADATA
p_requests-0.0.2.dist-info/WHEEL
p_requests-0.0.2.dist-info/top_level.txt
p_requests-0.0.2.dist-info/RECORD
