Metadata-Version: 2.4
Name: p_requests
Version: 0.0.2
Summary: Library for sending requests in parallel with retry
Home-page: https://github.com/VBenevides/p_requests
Author: Vinicius Benevides
Author-email: viniciusm.benevides@gmail.com
License: MIT
License-File: LICENSE
Requires-Dist: httpx
Dynamic: author
Dynamic: author-email
Dynamic: home-page
Dynamic: license
Dynamic: license-file
Dynamic: requires-dist
Dynamic: summary
